README.rst
setup.py
sysplan/__init__.py
sysplan/bash.py
sysplan/cli.py
sysplan/colors.py
sysplan/compose.py
sysplan/config.py
sysplan/diff.py
sysplan/docker.py
sysplan/files.py
sysplan/plan.py
sysplan/run.py
sysplan/systemd.py
sysplan.egg-info/PKG-INFO
sysplan.egg-info/SOURCES.txt
sysplan.egg-info/dependency_links.txt
sysplan.egg-info/entry_points.txt
sysplan.egg-info/requires.txt
sysplan.egg-info/top_level.txt