Metadata-Version: 2.1
Name: sysplan
Version: 0.0.1.dev47
Summary: quick system configuration tool
Home-page: https://yourlabs.io/oss/sysplan
Author: James Pic
Author-email: jamespic@gmail.com
License: MIT
Keywords: sysplan
Platform: UNKNOWN
Requires-Python: >=3.8
Provides-Extra: colors
Provides-Extra: test
